{
    "beer_sheva": [
        {
            "id": "bs_1",
            "name": "דניאל כהן"
        },
        {
            "id": "bs_2",
            "name": "אבי לוי"
        },
        {
            "id": "bs_3",
            "name": "מיכל שחר"
        },
        {
            "id": "bs_4",
            "name": "יוסי בניון"
        },
        {
            "id": "bs_5",
            "name": "נועה קירל"
        }
    ],
    "eilat": [
        {
            "id": "ei_1",
            "name": "יעל אברהמי"
        },
        {
            "id": "ei_2",
            "name": "עומר פרץ"
        },
        {
            "id": "ei_3",
            "name": "גל סופר"
        },
        {
            "id": "ei_4",
            "name": "סטטיק"
        },
        {
            "id": "ei_5",
            "name": "בן אל"
        }
    ]
}